kettled/__init__.py
kettled/__main__.py
kettled/constants/__init__.py
kettled/constants/date_formats.py
kettled/constants/env.py
kettled/constants/enums/__init__.py
kettled/constants/enums/commands_enum.py
kettled/constants/enums/enums_superclass.py
kettled/constants/enums/error_messages_enum.py
kettled/constants/enums/event_parameters_enum.py
kettled/constants/enums/fallback_options_enum.py
kettled/constants/enums/icons_enum.py
kettled/constants/enums/messages_enum.py
kettled/constants/enums/pipe_commands_enum.py
kettled/constants/enums/recurrency_options_enum.py
kettled/constants/enums/relative_datetime_options_enum.py
kettled/constants/enums/repository_event_parameters_enum.py
kettled/constants/enums/session_options_enum.py
kettled/constants/enums/terminal_prompts_enum.py
kettled/constants/enums/update_event_parameters_enum.py
kettled/constants/enums/weekdays_enum.py
kettled/daemon/__init__.py
kettled/daemon/daemon.py
kettled/daemon/pipes.py
kettled/daemon/scheduler.py
kettled/database/__init__.py
kettled/database/event_repository.py
kettled/handlers/__init__.py
kettled/handlers/handler.py
kettled/handlers/import_handler.py
kettled/handlers/terminal_handler.py
kettled/utils/__init__.py
kettled/utils/next_recurrency_calculator.py
kettled/utils/relative_datetime_calculator.py
kettled-1.1.0.dist-info/LICENSE
kettled-1.1.0.dist-info/METADATA
kettled-1.1.0.dist-info/WHEEL
kettled-1.1.0.dist-info/entry_points.txt
kettled-1.1.0.dist-info/top_level.txt
kettled-1.1.0.dist-info/RECORD
