Metadata-Version: 2.2
Name: kettled
Version: 1.1.0
Summary: A simple, ligthweight and secure python scheduler for UNIX systems that does not depend on any third-party packages.
Author-email: solarvenom <contact@solarvenom.com>
Maintainer-email: solarvenom <contact@solarvenom.com>
License: MIT
Project-URL: Homepage, https://github.com/solarvenom/kettled.py
Project-URL: Issue Tracker, https://github.com/solarvenom/kettled.py/issues
Project-URL: Changelog, https://github.com/solarvenom/kettled.py/CHANGELOG.md
Keywords: scheduler,schedule,daemon,datetime,date,time,timedelta
Classifier: Programming Language :: Python :: 3
Classifier: License :: OSI Approved :: MIT License
Classifier: Operating System :: Unix
Requires-Python: >=3.9
License-File: LICENSE
